{
  "stage_name": "Data Extraction",
  "yfinance_quality": {
    "success_rate": 0,
    "total_expected": 0,
    "total_found": 0,
    "companies_processed": [],
    "missing_companies": [],
    "status": "no_data_found"
  },
  "sec_edgar_quality": {
    "success_rate": 0.0,
    "total_expected": 30,
    "total_found": 0,
    "companies_processed": [],
    "document_types": {
      "10-K": 0,
      "10-Q": 0,
      "8-K": 0
    },
    "companies_with_sec_data": 0,
    "status": "failed"
  },
  "overall_success_rate": 0.0,
  "stage": "stage_01_extract",
  "partition": "20250819",
  "timestamp": "2025-08-19T11:35:16.706439",
  "build_id": "20250819_113516",
  "tier_name": "f2"
}